dtps/__init__.py
dtps/config.py
dtps/dtps_utils.py
dtps/ergo_create.py
dtps/ergo_ui.py
dtps/ergo_use.py
dtps/py.typed
dtps/structures.py
dtps_http/__init__.py
dtps_http/blob_manager.py
dtps_http/client.py
dtps_http/constants.py
dtps_http/ergo_utils.py
dtps_http/exceptions.py
dtps_http/link_headers.py
dtps_http/object_queue.py
dtps_http/py.typed
dtps_http/server.py
dtps_http/server_start.py
dtps_http/static/favicon.png
dtps_http/static/send.js
dtps_http/static/style.css
dtps_http/structures.py
dtps_http/types.py
dtps_http/types_of_source.py
dtps_http/urls.py
dtps_http/utils.py
dtps_http/utils_every_once_in_a_while.py
dtps_http_programs/__init__.py
dtps_http_programs/dtps_listen.py
dtps_http_programs/dtps_proxy.py
dtps_http_programs/dtps_send_continuous.py
dtps_http_programs/dtps_stats.py
dtps_http_programs/py.typed
dtps_http_programs/server_clock.py
dtps_http_programs/together.py
dtps_http-1.4.5.dist-info/METADATA
dtps_http-1.4.5.dist-info/WHEEL
dtps_http-1.4.5.dist-info/entry_points.txt
dtps_http-1.4.5.dist-info/licenses/LICENSE.pdf
dtps_http-1.4.5.dist-info/RECORD
