Metadata-Version: 2.4
Name: dtps-http
Version: 1.4.5
Summary: 
License-File: LICENSE.pdf
Author: Andrea Censi
Author-email: AndreaCensi@users.noreply.github.com
Requires-Python: >=3.8,<4.0
Classifier: Programming Language :: Python :: 3
Classifier: Programming Language :: Python :: 3.8
Classifier: Programming Language :: Python :: 3.9
Classifier: Programming Language :: Python :: 3.10
Classifier: Programming Language :: Python :: 3.11
Classifier: Programming Language :: Python :: 3.12
Classifier: Programming Language :: Python :: 3.13
Classifier: Programming Language :: Python :: 3.14
Requires-Dist: aiohttp (>=3,<4)
Requires-Dist: aiopubsub (>=3,<4)
Requires-Dist: cbor2 (>=5,<6)
Requires-Dist: jsonpatch (>=1.33,<2.0)
Requires-Dist: methodtools (>=0.4,<0.5)
Requires-Dist: prettyprinter (>=0.18.0,<0.19.0)
Requires-Dist: psutil (>=7,<8)
Requires-Dist: pydantic (==2.10.6)
Requires-Dist: pymdown-extensions (>=10,<11)
Requires-Dist: tcp_latency (==0.0.12)
Requires-Dist: timeout-decorator (>=0.5.0,<0.6.0)
Requires-Dist: typing_extensions (>=4,<5)
Requires-Dist: urllib3 (>=2,<3)
Requires-Dist: xxhash (>=3.4.1,<4.0.0)
